nvidia_pstate/__init__.py
nvidia_pstate/nvapi.py
nvidia_pstate/pstate.py
nvidia_pstate/pstate_nvapi.py
nvidia_pstate/scripts/nvidia_pstate.py
nvidia_pstate-1.0.5.post2.dist-info/LICENSE
nvidia_pstate-1.0.5.post2.dist-info/METADATA
nvidia_pstate-1.0.5.post2.dist-info/WHEEL
nvidia_pstate-1.0.5.post2.dist-info/entry_points.txt
nvidia_pstate-1.0.5.post2.dist-info/top_level.txt
nvidia_pstate-1.0.5.post2.dist-info/RECORD
