Metadata-Version: 2.1
Name: nvidia_pstate
Version: 1.0.5.post2
Summary: A library and CLI utilities for managing performance states of NVIDIA GPUs.
Author-email: sasha0552 <admin@sasha0552.org>
License: MIT
Project-URL: Homepage, https://github.com/sasha0552/nvidia-pstate
Classifier: Development Status :: 5 - Production/Stable
Classifier: Environment :: Console
Classifier: Intended Audience :: System Administrators
Classifier: License :: OSI Approved :: MIT License
Classifier: Programming Language :: Python
Classifier: Programming Language :: Python :: 3 :: Only
Classifier: Programming Language :: Python :: 3.8
Classifier: Programming Language :: Python :: 3.9
Classifier: Programming Language :: Python :: 3.10
Classifier: Programming Language :: Python :: 3.11
Classifier: Programming Language :: Python :: 3.12
Classifier: Topic :: System :: Hardware
License-File: LICENSE
